caching/__init__.py
caching/base.py
caching/config.py
caching/ext.py
caching/invalidation.py
django_cache_machine-1.0.0.dist-info/DESCRIPTION.rst
django_cache_machine-1.0.0.dist-info/METADATA
django_cache_machine-1.0.0.dist-info/RECORD
django_cache_machine-1.0.0.dist-info/WHEEL
django_cache_machine-1.0.0.dist-info/metadata.json
django_cache_machine-1.0.0.dist-info/top_level.txt
